{"tombImgMeta":[{"href":"http://ica.themorgan.org/icaimages/7/m751.001r.jpg","text":"MS M.751 fol. 1r"},{"href":"http://ica.themorgan.org/icaimages/7/m751.001v.jpg","text":"MS M.751 fol. 1v"},{"href":"http://ica.themorgan.org/icaimages/7/m751.002r.jpg","text":"MS M.751 fol. 2r"},{"href":"http://ica.themorgan.org/icaimages/7/m751.002v.jpg","text":"MS M.751 fol. 2v"},{"href":"http://ica.themorgan.org/icaimages/7/m751.003r.jpg","text":"MS M.751 fol. 3r"},{"href":"http://ica.themorgan.org/icaimages/7/m751.003v.jpg","text":"MS M.751 fol. 3v"},{"href":"http://ica.themorgan.org/icaimages/7/m751.004r.jpg","text":"MS M.751 fol. 4r"},{"href":"http://ica.themorgan.org/icaimages/7/m751.004v.jpg","text":"MS M.751 fol. 4v"},{"href":"http://ica.themorgan.org/icaimages/7/m751.005r.jpg","text":"MS M.751 fol. 5r"},{"href":"http://ica.themorgan.org/icaimages/7/m751.005v.jpg","text":"MS M.751 fol. 5v"},{"href":"http://ica.themorgan.org/icaimages/7/m751.006r.jpg","text":"MS M.751 fol. 6r"},{"href":"http://ica.themorgan.org/icaimages/7/m751.006v.jpg","text":"MS M.751 fol. 6v"},{"href":"http://ica.themorgan.org/icaimages/7/m751.007r.jpg","text":"MS M.751 fol. 7r"},{"href":"http://ica.themorgan.org/icaimages/7/m751.007v.jpg","text":"MS M.751 fol. 7v"},{"href":"http://ica.themorgan.org/icaimages/7/m751.008r.jpg","text":"MS M.751 fol. 8r"},{"href":"http://ica.themorgan.org/icaimages/7/m751.008v.jpg","text":"MS M.751 fol. 8v"},{"href":"http://ica.themorgan.org/icaimages/7/m751.009r.jpg","text":"MS M.751 fol. 9r"},{"href":"http://ica.themorgan.org/icaimages/7/m751.009v.jpg","text":"MS M.751 fol. 9v"},{"href":"http://ica.themorgan.org/icaimages/7/m751.010r.jpg","text":"MS M.751 fol. 10r"},{"href":"http://ica.themorgan.org/icaimages/7/m751.010v.jpg","text":"MS M.751 fol. 10v"},{"href":"http://ica.themorgan.org/icaimages/7/m751.011r.jpg","text":"MS M.751 fol. 11r"},{"href":"http://ica.themorgan.org/icaimages/7/m751.011v.jpg","text":"MS M.751 fol. 11v"},{"href":"http://ica.themorgan.org/icaimages/7/m751.012r.jpg","text":"MS M.751 fol. 12r"},{"href":"http://ica.themorgan.org/icaimages/7/m751.012v.jpg","text":"MS M.751 fol. 12v"},{"href":"http://ica.themorgan.org/icaimages/7/m751.013r.jpg","text":"MS M.751 fol. 13r"},{"href":"http://ica.themorgan.org/icaimages/7/m751.013v.jpg","text":"MS M.751 fol. 13v"},{"href":"http://ica.themorgan.org/icaimages/7/m751.014r.jpg","text":"MS M.751 fol. 14r"},{"href":"http://ica.themorgan.org/icaimages/7/m751.014v.jpg","text":"MS M.751 fol. 14v"},{"href":"http://ica.themorgan.org/icaimages/7/m751.015r.jpg","text":"MS M.751 fol. 15r"},{"href":"http://ica.themorgan.org/icaimages/7/m751.015v.jpg","text":"MS M.751 fol. 15v"},{"href":"http://ica.themorgan.org/icaimages/7/m751.016r.jpg","text":"MS M.751 fol. 16r"},{"href":"http://ica.themorgan.org/icaimages/7/m751.016v.jpg","text":"MS M.751 fol. 16v"},{"href":"http://ica.themorgan.org/icaimages/7/m751.017r.jpg","text":"MS M.751 fol. 17r"},{"href":"http://ica.themorgan.org/icaimages/7/m751.017v.jpg","text":"MS M.751 fol. 17v"},{"href":"http://ica.themorgan.org/icaimages/7/m751.018r.jpg","text":"MS M.751 fol. 18r"},{"href":"http://ica.themorgan.org/icaimages/7/m751.018v.jpg","text":"MS M.751 fol. 18v"},{"href":"http://ica.themorgan.org/icaimages/7/m751.019r.jpg","text":"MS M.751 fol. 19r"},{"href":"http://ica.themorgan.org/icaimages/7/m751.019v.jpg","text":"MS M.751 fol. 19v"},{"href":"http://ica.themorgan.org/icaimages/7/m751.020r.jpg","text":"MS M.751 fol. 20r"},{"href":"http://ica.themorgan.org/icaimages/7/m751.020v.jpg","text":"MS M.751 fol. 20v"},{"href":"http://ica.themorgan.org/icaimages/7/m751.021r.jpg","text":"MS M.751 fol. 21r"},{"href":"http://ica.themorgan.org/icaimages/7/m751.021v.jpg","text":"MS M.751 fol. 21v"},{"href":"http://ica.themorgan.org/icaimages/7/m751.022r.jpg","text":"MS M.751 fol. 22r"},{"href":"http://ica.themorgan.org/icaimages/7/m751.022v.jpg","text":"MS M.751 fol. 22v"},{"href":"http://ica.themorgan.org/icaimages/7/m751.023r.jpg","text":"MS M.751 fol. 23r"},{"href":"http://ica.themorgan.org/icaimages/7/m751.023v.jpg","text":"MS M.751 fol. 23v"},{"href":"http://ica.themorgan.org/icaimages/7/m751.024r.jpg","text":"MS M.751 fol. 24r"},{"href":"http://ica.themorgan.org/icaimages/7/m751.024v.jpg","text":"MS M.751 fol. 24v"},{"href":"http://ica.themorgan.org/icaimages/7/m751.025r.jpg","text":"MS M.751 fol. 25r"},{"href":"http://ica.themorgan.org/icaimages/7/m751.025v.jpg","text":"MS M.751 fol. 25v"},{"href":"http://ica.themorgan.org/icaimages/7/m751.026r.jpg","text":"MS M.751 fol. 26r"},{"href":"http://ica.themorgan.org/icaimages/7/m751.026v.jpg","text":"MS M.751 fol. 26v"},{"href":"http://ica.themorgan.org/icaimages/7/m751.027r.jpg","text":"MS M.751 fol. 27r"},{"href":"http://ica.themorgan.org/icaimages/7/m751.027v.jpg","text":"MS M.751 fol. 27v"},{"href":"http://ica.themorgan.org/icaimages/7/m751.028r.jpg","text":"MS M.751 fol. 28r"},{"href":"http://ica.themorgan.org/icaimages/7/m751.028v.jpg","text":"MS M.751 fol. 28v"},{"href":"http://ica.themorgan.org/icaimages/7/m751.029r.jpg","text":"MS M.751 fol. 29r"},{"href":"http://ica.themorgan.org/icaimages/7/m751.029v.jpg","text":"MS M.751 fol. 29v"},{"href":"http://ica.themorgan.org/icaimages/7/m751.030r.jpg","text":"MS M.751 fol. 30r"},{"href":"http://ica.themorgan.org/icaimages/7/m751.030v.jpg","text":"MS M.751 fol. 30v"},{"href":"http://ica.themorgan.org/icaimages/7/m751.031r.jpg","text":"MS M.751 fol. 31r"},{"href":"http://ica.themorgan.org/icaimages/7/m751.031v.jpg","text":"MS M.751 fol. 31v"},{"href":"http://ica.themorgan.org/icaimages/7/m751.032r.jpg","text":"MS M.751 fol. 32r"},{"href":"http://ica.themorgan.org/icaimages/7/m751.032v.jpg","text":"MS M.751 fol. 32v"},{"href":"http://ica.themorgan.org/icaimages/7/m751.033r.jpg","text":"MS M.751 fol. 33r"},{"href":"http://ica.themorgan.org/icaimages/7/m751.033v.jpg","text":"MS M.751 fol. 33v"},{"href":"http://ica.themorgan.org/icaimages/7/m751.034r.jpg","text":"MS M.751 fol. 34r"},{"href":"http://ica.themorgan.org/icaimages/7/m751.034v.jpg","text":"MS M.751 fol. 34v"},{"href":"http://ica.themorgan.org/icaimages/7/m751.035r.jpg","text":"MS M.751 fol. 35r"},{"href":"http://ica.themorgan.org/icaimages/7/m751.035v.jpg","text":"MS M.751 fol. 35v"},{"href":"http://ica.themorgan.org/icaimages/7/m751.036r.jpg","text":"MS M.751 fol. 36r"},{"href":"http://ica.themorgan.org/icaimages/7/m751.036v.jpg","text":"MS M.751 fol. 36v"},{"href":"http://ica.themorgan.org/icaimages/7/m751.037r.jpg","text":"MS M.751 fol. 37r"},{"href":"http://ica.themorgan.org/icaimages/7/m751.037v.jpg","text":"MS M.751 fol. 37v"},{"href":"http://ica.themorgan.org/icaimages/7/m751.038r.jpg","text":"MS M.751 fol. 38r"},{"href":"http://ica.themorgan.org/icaimages/7/m751.038v.jpg","text":"MS M.751 fol. 38v"},{"href":"http://ica.themorgan.org/icaimages/7/m751.039r.jpg","text":"MS M.751 fol. 39r"},{"href":"http://ica.themorgan.org/icaimages/7/m751.039v.jpg","text":"MS M.751 fol. 39v"},{"href":"http://ica.themorgan.org/icaimages/7/m751.040r.jpg","text":"MS M.751 fol. 40r"},{"href":"http://ica.themorgan.org/icaimages/7/m751.040v.jpg","text":"MS M.751 fol. 40v"},{"href":"http://ica.themorgan.org/icaimages/7/m751.041r.jpg","text":"MS M.751 fol. 41r"},{"href":"http://ica.themorgan.org/icaimages/7/m751.041v.jpg","text":"MS M.751 fol. 41v"},{"href":"http://ica.themorgan.org/icaimages/7/m751.042r.jpg","text":"MS M.751 fol. 42r"},{"href":"http://ica.themorgan.org/icaimages/7/m751.042v.jpg","text":"MS M.751 fol. 42v"},{"href":"http://ica.themorgan.org/icaimages/7/m751.043r.jpg","text":"MS M.751 fol. 43r"},{"href":"http://ica.themorgan.org/icaimages/7/m751.043v.jpg","text":"MS M.751 fol. 43v"},{"href":"http://ica.themorgan.org/icaimages/7/m751.044r.jpg","text":"MS M.751 fol. 44r"},{"href":"http://ica.themorgan.org/icaimages/7/m751.044v.jpg","text":"MS M.751 fol. 44v"},{"href":"http://ica.themorgan.org/icaimages/7/m751.045r.jpg","text":"MS M.751 fol. 45r"},{"href":"http://ica.themorgan.org/icaimages/7/m751.045v.jpg","text":"MS M.751 fol. 45v"},{"href":"http://ica.themorgan.org/icaimages/7/m751.046r.jpg","text":"MS M.751 fol. 46r"},{"href":"http://ica.themorgan.org/icaimages/7/m751.046v.jpg","text":"MS M.751 fol. 46v"},{"href":"http://ica.themorgan.org/icaimages/7/m751.047r.jpg","text":"MS M.751 fol. 47r"},{"href":"http://ica.themorgan.org/icaimages/7/m751.047v.jpg","text":"MS M.751 fol. 47v"},{"href":"http://ica.themorgan.org/icaimages/7/m751.048r.jpg","text":"MS M.751 fol. 48r"},{"href":"http://ica.themorgan.org/icaimages/7/m751.048v.jpg","text":"MS M.751 fol. 48v"},{"href":"http://ica.themorgan.org/icaimages/7/m751.049r.jpg","text":"MS M.751 fol. 49r"},{"href":"http://ica.themorgan.org/icaimages/7/m751.049v.jpg","text":"MS M.751 fol. 49v"},{"href":"http://ica.themorgan.org/icaimages/7/m751.050r.jpg","text":"MS M.751 fol. 50r"},{"href":"http://ica.themorgan.org/icaimages/7/m751.050v.jpg","text":"MS M.751 fol. 50v"},{"href":"http://ica.themorgan.org/icaimages/7/m751.051r.jpg","text":"MS M.751 fol. 51r"},{"href":"http://ica.themorgan.org/icaimages/7/m751.051v.jpg","text":"MS M.751 fol. 51v"},{"href":"http://ica.themorgan.org/icaimages/7/m751.052r.jpg","text":"MS M.751 fol. 52r"},{"href":"http://ica.themorgan.org/icaimages/7/m751.052v.jpg","text":"MS M.751 fol. 52v"},{"href":"http://ica.themorgan.org/icaimages/7/m751.053r.jpg","text":"MS M.751 fol. 53r"},{"href":"http://ica.themorgan.org/icaimages/7/m751.053v.jpg","text":"MS M.751 fol. 53v"},{"href":"http://ica.themorgan.org/icaimages/7/m751.054r.jpg","text":"MS M.751 fol. 54r"},{"href":"http://ica.themorgan.org/icaimages/7/m751.054v.jpg","text":"MS M.751 fol. 54v"},{"href":"http://ica.themorgan.org/icaimages/7/m751.055r.jpg","text":"MS M.751 fol. 55r"},{"href":"http://ica.themorgan.org/icaimages/7/m751.055v.jpg","text":"MS M.751 fol. 55v"},{"href":"http://ica.themorgan.org/icaimages/7/m751.056r.jpg","text":"MS M.751 fol. 56r"},{"href":"http://ica.themorgan.org/icaimages/7/m751.056v.jpg","text":"MS M.751 fol. 56v"},{"href":"http://ica.themorgan.org/icaimages/7/m751.057r.jpg","text":"MS M.751 fol. 57r"},{"href":"http://ica.themorgan.org/icaimages/7/m751.057v.jpg","text":"MS M.751 fol. 57v"},{"href":"http://ica.themorgan.org/icaimages/7/m751.058r.jpg","text":"MS M.751 fol. 58r"},{"href":"http://ica.themorgan.org/icaimages/7/m751.058v.jpg","text":"MS M.751 fol. 58v"},{"href":"http://ica.themorgan.org/icaimages/7/m751.059r.jpg","text":"MS M.751 fol. 59r"},{"href":"http://ica.themorgan.org/icaimages/7/m751.059v.jpg","text":"MS M.751 fol. 59v"},{"href":"http://ica.themorgan.org/icaimages/7/m751.060r.jpg","text":"MS M.751 fol. 60r"},{"href":"http://ica.themorgan.org/icaimages/7/m751.060v.jpg","text":"MS M.751 fol. 60v"},{"href":"http://ica.themorgan.org/icaimages/7/m751.061r.jpg","text":"MS M.751 fol. 61r"},{"href":"http://ica.themorgan.org/icaimages/7/m751.061v.jpg","text":"MS M.751 fol. 61v"},{"href":"http://ica.themorgan.org/icaimages/7/m751.062r.jpg","text":"MS M.751 fol. 62r"},{"href":"http://ica.themorgan.org/icaimages/7/m751.062v.jpg","text":"MS M.751 fol. 62v"},{"href":"http://ica.themorgan.org/icaimages/7/m751.063r.jpg","text":"MS M.751 fol. 63r"},{"href":"http://ica.themorgan.org/icaimages/7/m751.063v.jpg","text":"MS M.751 fol. 63v"},{"href":"http://ica.themorgan.org/icaimages/7/m751.064r.jpg","text":"MS M.751 fol. 64r"},{"href":"http://ica.themorgan.org/icaimages/7/m751.064v.jpg","text":"MS M.751 fol. 64v"},{"href":"http://ica.themorgan.org/icaimages/7/m751.065r.jpg","text":"MS M.751 fol. 65r"},{"href":"http://ica.themorgan.org/icaimages/7/m751.065v.jpg","text":"MS M.751 fol. 65v"},{"href":"http://ica.themorgan.org/icaimages/7/m751.066r.jpg","text":"MS M.751 fol. 66r"},{"href":"http://ica.themorgan.org/icaimages/7/m751.066v.jpg","text":"MS M.751 fol. 66v"},{"href":"http://ica.themorgan.org/icaimages/7/m751.067r.jpg","text":"MS M.751 fol. 67r"},{"href":"http://ica.themorgan.org/icaimages/7/m751.067v.jpg","text":"MS M.751 fol. 67v"},{"href":"http://ica.themorgan.org/icaimages/7/m751.068r.jpg","text":"MS M.751 fol. 68r"},{"href":"http://ica.themorgan.org/icaimages/7/m751.068v.jpg","text":"MS M.751 fol. 68v"},{"href":"http://ica.themorgan.org/icaimages/7/m751.069r.jpg","text":"MS M.751 fol. 69r"},{"href":"http://ica.themorgan.org/icaimages/7/m751.069v.jpg","text":"MS M.751 fol. 69v"},{"href":"http://ica.themorgan.org/icaimages/7/m751.070r.jpg","text":"MS M.751 fol. 70r"},{"href":"http://ica.themorgan.org/icaimages/7/m751.070v.jpg","text":"MS M.751 fol. 70v"},{"href":"http://ica.themorgan.org/icaimages/7/m751.071r.jpg","text":"MS M.751 fol. 71r"},{"href":"http://ica.themorgan.org/icaimages/7/m751.071v.jpg","text":"MS M.751 fol. 71v"},{"href":"http://ica.themorgan.org/icaimages/7/m751.072r.jpg","text":"MS M.751 fol. 72r"},{"href":"http://ica.themorgan.org/icaimages/7/m751.072v.jpg","text":"MS M.751 fol. 72v"},{"href":"http://ica.themorgan.org/icaimages/7/m751.073r.jpg","text":"MS M.751 fol. 73r"},{"href":"http://ica.themorgan.org/icaimages/7/m751.073v.jpg","text":"MS M.751 fol. 73v"},{"href":"http://ica.themorgan.org/icaimages/7/m751.074r.jpg","text":"MS M.751 fol. 74r"},{"href":"http://ica.themorgan.org/icaimages/7/m751.074v.jpg","text":"MS M.751 fol. 74v"},{"href":"http://ica.themorgan.org/icaimages/7/m751.075r.jpg","text":"MS M.751 fol. 75r"},{"href":"http://ica.themorgan.org/icaimages/7/m751.075v.jpg","text":"MS M.751 fol. 75v"},{"href":"http://ica.themorgan.org/icaimages/7/m751.076r.jpg","text":"MS M.751 fol. 76r"},{"href":"http://ica.themorgan.org/icaimages/7/m751.076v.jpg","text":"MS M.751 fol. 76v"},{"href":"http://ica.themorgan.org/icaimages/7/m751.077r.jpg","text":"MS M.751 fol. 77r"},{"href":"http://ica.themorgan.org/icaimages/7/m751.077v.jpg","text":"MS M.751 fol. 77v"},{"href":"http://ica.themorgan.org/icaimages/7/m751.078r.jpg","text":"MS M.751 fol. 78r"},{"href":"http://ica.themorgan.org/icaimages/7/m751.078v.jpg","text":"MS M.751 fol. 78v"},{"href":"http://ica.themorgan.org/icaimages/7/m751.079r.jpg","text":"MS M.751 fol. 79r"},{"href":"http://ica.themorgan.org/icaimages/7/m751.079v.jpg","text":"MS M.751 fol. 79v"},{"href":"http://ica.themorgan.org/icaimages/7/m751.080r.jpg","text":"MS M.751 fol. 80r"},{"href":"http://ica.themorgan.org/icaimages/7/m751.080v.jpg","text":"MS M.751 fol. 80v"},{"href":"http://ica.themorgan.org/icaimages/7/m751.081r.jpg","text":"MS M.751 fol. 81r"},{"href":"http://ica.themorgan.org/icaimages/7/m751.081v.jpg","text":"MS M.751 fol. 81v"},{"href":"http://ica.themorgan.org/icaimages/7/m751.082r.jpg","text":"MS M.751 fol. 82r"},{"href":"http://ica.themorgan.org/icaimages/7/m751.082v.jpg","text":"MS M.751 fol. 82v"},{"href":"http://ica.themorgan.org/icaimages/7/m751.083r.jpg","text":"MS M.751 fol. 83r"},{"href":"http://ica.themorgan.org/icaimages/7/m751.083v.jpg","text":"MS M.751 fol. 83v"},{"href":"http://ica.themorgan.org/icaimages/7/m751.084r.jpg","text":"MS M.751 fol. 84r"},{"href":"http://ica.themorgan.org/icaimages/7/m751.084v.jpg","text":"MS M.751 fol. 84v"},{"href":"http://ica.themorgan.org/icaimages/7/m751.085r.jpg","text":"MS M.751 fol. 85r"},{"href":"http://ica.themorgan.org/icaimages/7/m751.085v.jpg","text":"MS M.751 fol. 85v"},{"href":"http://ica.themorgan.org/icaimages/7/m751.086r.jpg","text":"MS M.751 fol. 86r"},{"href":"http://ica.themorgan.org/icaimages/7/m751.086v.jpg","text":"MS M.751 fol. 86v"},{"href":"http://ica.themorgan.org/icaimages/7/m751.087r.jpg","text":"MS M.751 fol. 87r"},{"href":"http://ica.themorgan.org/icaimages/7/m751.087v.jpg","text":"MS M.751 fol. 87v"},{"href":"http://ica.themorgan.org/icaimages/7/m751.088r.jpg","text":"MS M.751 fol. 88r"},{"href":"http://ica.themorgan.org/icaimages/7/m751.088v.jpg","text":"MS M.751 fol. 88v"},{"href":"http://ica.themorgan.org/icaimages/7/m751.089r.jpg","text":"MS M.751 fol. 89r"},{"href":"http://ica.themorgan.org/icaimages/7/m751.089v.jpg","text":"MS M.751 fol. 89v"},{"href":"http://ica.themorgan.org/icaimages/7/m751.090r.jpg","text":"MS M.751 fol. 90r"},{"href":"http://ica.themorgan.org/icaimages/7/m751.090v.jpg","text":"MS M.751 fol. 90v"},{"href":"http://ica.themorgan.org/icaimages/7/m751.091r.jpg","text":"MS M.751 fol. 91r"},{"href":"http://ica.themorgan.org/icaimages/7/m751.091v.jpg","text":"MS M.751 fol. 91v"},{"href":"http://ica.themorgan.org/icaimages/7/m751.092r.jpg","text":"MS M.751 fol. 92r"},{"href":"http://ica.themorgan.org/icaimages/7/m751.092v.jpg","text":"MS M.751 fol. 92v"},{"href":"http://ica.themorgan.org/icaimages/7/m751.093r.jpg","text":"MS M.751 fol. 93r"},{"href":"http://ica.themorgan.org/icaimages/7/m751.093v.jpg","text":"MS M.751 fol. 93v"},{"href":"http://ica.themorgan.org/icaimages/7/m751.094r.jpg","text":"MS M.751 fol. 94r"},{"href":"http://ica.themorgan.org/icaimages/7/m751.094v.jpg","text":"MS M.751 fol. 94v"},{"href":"http://ica.themorgan.org/icaimages/7/m751.095r.jpg","text":"MS M.751 fol. 95r"},{"href":"http://ica.themorgan.org/icaimages/7/m751.095v.jpg","text":"MS M.751 fol. 95v"},{"href":"http://ica.themorgan.org/icaimages/7/m751.096r.jpg","text":"MS M.751 fol. 96r"},{"href":"http://ica.themorgan.org/icaimages/7/m751.096v.jpg","text":"MS M.751 fol. 96v"},{"href":"http://ica.themorgan.org/icaimages/7/m751.097r.jpg","text":"MS M.751 fol. 97r"},{"href":"http://ica.themorgan.org/icaimages/7/m751.097v.jpg","text":"MS M.751 fol. 97v"},{"href":"http://ica.themorgan.org/icaimages/7/m751.098r.jpg","text":"MS M.751 fol. 98r"},{"href":"http://ica.themorgan.org/icaimages/7/m751.098v.jpg","text":"MS M.751 fol. 98v"},{"href":"http://ica.themorgan.org/icaimages/7/m751.099r.jpg","text":"MS M.751 fol. 99r"},{"href":"http://ica.themorgan.org/icaimages/7/m751.099v.jpg","text":"MS M.751 fol. 99v"},{"href":"http://ica.themorgan.org/icaimages/7/m751.100r.jpg","text":"MS M.751 fol. 100r"},{"href":"http://ica.themorgan.org/icaimages/7/m751.100v.jpg","text":"MS M.751 fol. 100v"},{"href":"http://ica.themorgan.org/icaimages/7/m751.101r.jpg","text":"MS M.751 fol. 101r"},{"href":"http://ica.themorgan.org/icaimages/7/m751.101v.jpg","text":"MS M.751 fol. 101v"},{"href":"http://ica.themorgan.org/icaimages/7/m751.102r.jpg","text":"MS M.751 fol. 102r"},{"href":"http://ica.themorgan.org/icaimages/7/m751.102v.jpg","text":"MS M.751 fol. 102v"},{"href":"http://ica.themorgan.org/icaimages/7/m751.103r.jpg","text":"MS M.751 fol. 103r"},{"href":"http://ica.themorgan.org/icaimages/7/m751.103v.jpg","text":"MS M.751 fol. 103v"},{"href":"http://ica.themorgan.org/icaimages/7/m751.104r.jpg","text":"MS M.751 fol. 104r"},{"href":"http://ica.themorgan.org/icaimages/7/m751.104v.jpg","text":"MS M.751 fol. 104v"},{"href":"http://ica.themorgan.org/icaimages/7/m751.105r.jpg","text":"MS M.751 fol. 105r"},{"href":"http://ica.themorgan.org/icaimages/7/m751.105v.jpg","text":"MS M.751 fol. 105v"},{"href":"http://ica.themorgan.org/icaimages/7/m751.106r.jpg","text":"MS M.751 fol. 106r"},{"href":"http://ica.themorgan.org/icaimages/7/m751.106v.jpg","text":"MS M.751 fol. 106v"},{"href":"http://ica.themorgan.org/icaimages/7/m751.107r.jpg","text":"MS M.751 fol. 107r"},{"href":"http://ica.themorgan.org/icaimages/7/m751.107v.jpg","text":"MS M.751 fol. 107v"},{"href":"http://ica.themorgan.org/icaimages/7/m751.108r.jpg","text":"MS M.751 fol. 108r"},{"href":"http://ica.themorgan.org/icaimages/7/m751.108v.jpg","text":"MS M.751 fol. 108v"},{"href":"http://ica.themorgan.org/icaimages/7/m751.109r.jpg","text":"MS M.751 fol. 109r"},{"href":"http://ica.themorgan.org/icaimages/7/m751.109v.jpg","text":"MS M.751 fol. 109v"},{"href":"http://ica.themorgan.org/icaimages/7/m751.110r.jpg","text":"MS M.751 fol. 110r"},{"href":"http://ica.themorgan.org/icaimages/7/m751.110v.jpg","text":"MS M.751 fol. 110v"},{"href":"http://ica.themorgan.org/icaimages/7/m751.111r.jpg","text":"MS M.751 fol. 111r"},{"href":"http://ica.themorgan.org/icaimages/7/m751.111v.jpg","text":"MS M.751 fol. 111v"},{"href":"http://ica.themorgan.org/icaimages/7/m751.112r.jpg","text":"MS M.751 fol. 112r"},{"href":"http://ica.themorgan.org/icaimages/7/m751.112v.jpg","text":"MS M.751 fol. 112v"},{"href":"http://ica.themorgan.org/icaimages/7/m751.113r.jpg","text":"MS M.751 fol. 113r"},{"href":"http://ica.themorgan.org/icaimages/7/m751.113v.jpg","text":"MS M.751 fol. 113v"},{"href":"http://ica.themorgan.org/icaimages/7/m751.114r.jpg","text":"MS M.751 fol. 114r"},{"href":"http://ica.themorgan.org/icaimages/7/m751.114v.jpg","text":"MS M.751 fol. 114v"}],"tombMeta":{"tombInfo":{"tombName":"MS M.751 (fasimile)","title":"Abrégé des histoires divines","date":"1300","location":"possibly Amiens","font":"minuscule","current_lib":"morgan library"}}}